etnltk/__init__.py
etnltk/common/__init__.py
etnltk/common/doc.py
etnltk/lang/__init__.py
etnltk/lang/am/__init__.py
etnltk/lang/am/normalizer.py
etnltk/lang/am/preprocessing.py
etnltk/lang/am/punctuation.py
etnltk/lang/am/stop_words.py
etnltk/lang/am/utils.py
etnltk/lang/am/data/__init__.py
etnltk/lang/am/data/char_replacers_dict.json
etnltk/lang/am/data/labialized_dict.json
etnltk/lang/am/data/punct_replacers_dict.json
etnltk/lang/am/data/shortened_expansions_dict.json
etnltk/tokenize/__init__.py
etnltk/tokenize/am.py
etnltk/tokenize/line.py
etnltk/tokenize/or.py
etnltk/tokenize/regexp.py
etnltk/tokenize/space.py
etnltk-0.0.22.dist-info/LICENSE.txt
etnltk-0.0.22.dist-info/METADATA
etnltk-0.0.22.dist-info/WHEEL
etnltk-0.0.22.dist-info/top_level.txt
etnltk-0.0.22.dist-info/RECORD
