Metadata-Version: 2.1
Name: etnltk
Version: 0.0.22
Summary: Ethiopian Natural Language Toolkit
Home-page: https://github.com/robikieq/etnltk.git
Author: Robel Equbasilassie
Author-email: robiki4life@gmail.com
Keywords: ['nlp','ethiopic','amharic','tokenization','preprocessing','text-analytics']
Classifier: Programming Language :: Python :: 3
Classifier: License :: OSI Approved :: MIT License
Classifier: Operating System :: OS Independent
Requires-Python: >=3.6
License-File: LICENSE.txt
Requires-Dist: textsearch (>=0.0.21)
Requires-Dist: emoji (>=1.7.0)
